{"agowskyy":{"cher Fall":11.0,"tungen Asia":27.0,"tungen Japan":25.0,"K\u00f6cher Fall":null,"T\u00f6tungen Asia":null,"T\u00f6tungen Japan":null,"cher Asia":null,"K\u00f6cher Asia":null},"Anni808":{"cher Fall":14.0,"tungen Asia":20.0,"tungen Japan":19.0,"K\u00f6cher Fall":null,"T\u00f6tungen Asia":null,"T\u00f6tungen Japan":null,"cher Asia":null,"K\u00f6cher Asia":null},"Axollotel":{"cher Fall":13.0,"tungen Asia":23.0,"tungen Japan":18.0,"K\u00f6cher Fall":null,"T\u00f6tungen Asia":null,"T\u00f6tungen Japan":null,"cher Asia":null,"K\u00f6cher Asia":null},"BacardiSprite":{"cher Fall":15.0,"tungen Asia":19.0,"tungen Japan":24.0,"K\u00f6cher Fall":null,"T\u00f6tungen Asia":null,"T\u00f6tungen Japan":null,"cher Asia":null,"K\u00f6cher Asia":null},"bawskey":{"cher Fall":9.0,"tungen Asia":25.0,"tungen Japan":26.0,"K\u00f6cher Fall":null,"T\u00f6tungen Asia":null,"T\u00f6tungen Japan":null,"cher Asia":null,"K\u00f6cher Asia":null},"BearchenGott":{"cher Fall":21.0,"tungen Asia":30.0,"tungen Japan":34.0,"K\u00f6cher Fall":null,"T\u00f6tungen Asia":null,"T\u00f6tungen Japan":null,"cher Asia":null,"K\u00f6cher Asia":null},"BusinessBent":{"cher Fall":8.0,"tungen Asia":19.0,"tungen Japan":25.0,"K\u00f6cher Fall":null,"T\u00f6tungen Asia":null,"T\u00f6tungen Japan":null,"cher Asia":null,"K\u00f6cher Asia":null},"byTobi":{"cher Fall":20.0,"tungen Asia":24.0,"tungen Japan":43.0,"K\u00f6cher Fall":null,"T\u00f6tungen Asia":null,"T\u00f6tungen Japan":null,"cher Asia":null,"K\u00f6cher Asia":null},"cediiiiii_10":{"cher Fall":null,"tungen Asia":null,"tungen Japan":null,"K\u00f6cher Fall":26.0,"T\u00f6tungen Asia":31.0,"T\u00f6tungen Japan":38.0,"cher Asia":null,"K\u00f6cher Asia":null},"Chander24":{"cher Fall":14.0,"tungen Asia":16.0,"tungen Japan":19.0,"K\u00f6cher Fall":null,"T\u00f6tungen Asia":null,"T\u00f6tungen Japan":null,"cher Asia":null,"K\u00f6cher Asia":null},"Chrisi20101":{"cher Fall":null,"tungen Asia":null,"tungen Japan":null,"K\u00f6cher Fall":14.0,"T\u00f6tungen Asia":20.0,"T\u00f6tungen Japan":23.0,"cher Asia":null,"K\u00f6cher Asia":null},"crocodile1870":{"cher Fall":10.0,"tungen Asia":16.0,"tungen Japan":16.0,"K\u00f6cher Fall":null,"T\u00f6tungen Asia":null,"T\u00f6tungen Japan":null,"cher Asia":null,"K\u00f6cher Asia":null},"cxl1lo":{"cher Fall":13.0,"tungen Asia":22.0,"tungen Japan":16.0,"K\u00f6cher Fall":null,"T\u00f6tungen Asia":null,"T\u00f6tungen Japan":null,"cher Asia":null,"K\u00f6cher Asia":null},"DarkCobweb":{"cher Fall":17.0,"tungen Asia":26.0,"tungen Japan":26.0,"K\u00f6cher Fall":null,"T\u00f6tungen Asia":null,"T\u00f6tungen Japan":null,"cher Asia":null,"K\u00f6cher Asia":null},"DerBaumIstDerWeg":{"cher Fall":23.0,"tungen Asia":26.0,"tungen Japan":37.0,"K\u00f6cher Fall":null,"T\u00f6tungen Asia":null,"T\u00f6tungen Japan":null,"cher Asia":null,"K\u00f6cher Asia":null},"Ex4cted":{"cher Fall":null,"tungen Asia":null,"tungen Japan":null,"K\u00f6cher Fall":17.0,"T\u00f6tungen Asia":31.0,"T\u00f6tungen Japan":27.0,"cher Asia":null,"K\u00f6cher Asia":null},"Falke23_5":{"cher Fall":null,"tungen Asia":null,"tungen Japan":30.0,"K\u00f6cher Fall":null,"T\u00f6tungen Asia":null,"T\u00f6tungen Japan":null,"cher Asia":27.0,"K\u00f6cher Asia":null},"Feinberg":{"cher Fall":null,"tungen Asia":null,"tungen Japan":25.0,"K\u00f6cher Fall":null,"T\u00f6tungen Asia":null,"T\u00f6tungen Japan":null,"cher Asia":20.0,"K\u00f6cher Asia":null},"Fflopse":{"cher Fall":null,"tungen Asia":null,"tungen Japan":null,"K\u00f6cher Fall":28.0,"T\u00f6tungen Asia":42.0,"T\u00f6tungen Japan":40.0,"cher Asia":null,"K\u00f6cher Asia":null},"ForceFox":{"cher Fall":11.0,"tungen Asia":21.0,"tungen Japan":23.0,"K\u00f6cher Fall":null,"T\u00f6tungen Asia":null,"T\u00f6tungen Japan":null,"cher Asia":null,"K\u00f6cher Asia":null},"Freeeedom":{"cher Fall":null,"tungen Asia":null,"tungen Japan":null,"K\u00f6cher Fall":17.0,"T\u00f6tungen Asia":25.0,"T\u00f6tungen Japan":27.0,"cher Asia":null,"K\u00f6cher Asia":null},"frutigall":{"cher Fall":17.0,"tungen Asia":28.0,"tungen Japan":26.0,"K\u00f6cher Fall":null,"T\u00f6tungen Asia":null,"T\u00f6tungen Japan":null,"cher Asia":null,"K\u00f6cher Asia":null},"GeneralEnte06":{"cher Fall":null,"tungen Asia":null,"tungen Japan":null,"K\u00f6cher Fall":18.0,"T\u00f6tungen Asia":28.0,"T\u00f6tungen Japan":29.0,"cher Asia":null,"K\u00f6cher Asia":null},"Gerrygames":{"cher Fall":null,"tungen Asia":null,"tungen Japan":33.0,"K\u00f6cher Fall":null,"T\u00f6tungen Asia":null,"T\u00f6tungen Japan":null,"cher Asia":32.0,"K\u00f6cher Asia":null},"Gobo9":{"cher Fall":null,"tungen Asia":null,"tungen Japan":null,"K\u00f6cher Fall":26.0,"T\u00f6tungen Asia":33.0,"T\u00f6tungen Japan":32.0,"cher Asia":null,"K\u00f6cher Asia":null},"GrafikKatze":{"cher Fall":null,"tungen Asia":null,"tungen Japan":21.0,"K\u00f6cher Fall":null,"T\u00f6tungen Asia":null,"T\u00f6tungen Japan":null,"cher Asia":22.0,"K\u00f6cher Asia":null},"Grapfen":{"cher Fall":25.0,"tungen Asia":31.0,"tungen Japan":32.0,"K\u00f6cher Fall":null,"T\u00f6tungen Asia":null,"T\u00f6tungen Japan":null,"cher Asia":null,"K\u00f6cher Asia":null},"H1ghsay":{"cher Fall":null,"tungen Asia":null,"tungen Japan":null,"K\u00f6cher Fall":22.0,"T\u00f6tungen Asia":20.0,"T\u00f6tungen Japan":21.0,"cher Asia":null,"K\u00f6cher Asia":null},"h4nnes":{"cher Fall":24.0,"tungen Asia":35.0,"tungen Japan":33.0,"K\u00f6cher Fall":null,"T\u00f6tungen Asia":null,"T\u00f6tungen Japan":null,"cher Asia":null,"K\u00f6cher Asia":null},"Harold_Sensemann":{"cher Fall":17.0,"tungen Asia":25.0,"tungen Japan":26.0,"K\u00f6cher Fall":null,"T\u00f6tungen Asia":null,"T\u00f6tungen Japan":null,"cher Asia":null,"K\u00f6cher Asia":null},"HerrDante":{"cher Fall":29.0,"tungen Asia":36.0,"tungen Japan":38.0,"K\u00f6cher Fall":null,"T\u00f6tungen Asia":null,"T\u00f6tungen Japan":null,"cher Asia":null,"K\u00f6cher Asia":null},"Jan2220":{"cher Fall":15.0,"tungen Asia":26.0,"tungen Japan":21.0,"K\u00f6cher Fall":null,"T\u00f6tungen Asia":null,"T\u00f6tungen Japan":null,"cher Asia":null,"K\u00f6cher Asia":null},"JennieKim":{"cher Fall":17.0,"tungen Asia":26.0,"tungen Japan":25.0,"K\u00f6cher Fall":null,"T\u00f6tungen Asia":null,"T\u00f6tungen Japan":null,"cher Asia":null,"K\u00f6cher Asia":null},"jimmi1410":{"cher Fall":13.0,"tungen Asia":16.0,"tungen Japan":14.0,"K\u00f6cher Fall":null,"T\u00f6tungen Asia":null,"T\u00f6tungen Japan":null,"cher Asia":null,"K\u00f6cher Asia":null},"JOW23":{"cher Fall":25.0,"tungen Asia":34.0,"tungen Japan":32.0,"K\u00f6cher Fall":null,"T\u00f6tungen Asia":null,"T\u00f6tungen Japan":null,"cher Asia":null,"K\u00f6cher Asia":null},"Joy_8oy":{"cher Fall":17.0,"tungen Asia":19.0,"tungen Japan":18.0,"K\u00f6cher Fall":null,"T\u00f6tungen Asia":null,"T\u00f6tungen Japan":null,"cher Asia":null,"K\u00f6cher Asia":null},"JustK1lling":{"cher Fall":16.0,"tungen Asia":18.0,"tungen Japan":22.0,"K\u00f6cher Fall":null,"T\u00f6tungen Asia":null,"T\u00f6tungen Japan":null,"cher Asia":null,"K\u00f6cher Asia":null},"KakaMC":{"cher Fall":19.0,"tungen Asia":24.0,"tungen Japan":25.0,"K\u00f6cher Fall":null,"T\u00f6tungen Asia":null,"T\u00f6tungen Japan":null,"cher Asia":null,"K\u00f6cher Asia":null},"Kanickelul":{"cher Fall":null,"tungen Asia":null,"tungen Japan":null,"K\u00f6cher Fall":null,"T\u00f6tungen Asia":null,"T\u00f6tungen Japan":13.0,"cher Asia":null,"K\u00f6cher Asia":18.0},"Kokochampi":{"cher Fall":null,"tungen Asia":null,"tungen Japan":16.0,"K\u00f6cher Fall":null,"T\u00f6tungen Asia":null,"T\u00f6tungen Japan":null,"cher Asia":17.0,"K\u00f6cher Asia":null},"Kokochampo":{"cher Fall":9.0,"tungen Asia":23.0,"tungen Japan":18.0,"K\u00f6cher Fall":null,"T\u00f6tungen Asia":null,"T\u00f6tungen Japan":null,"cher Asia":null,"K\u00f6cher Asia":null},"Kyuudo":{"cher Fall":21.0,"tungen Asia":26.0,"tungen Japan":22.0,"K\u00f6cher Fall":null,"T\u00f6tungen Asia":null,"T\u00f6tungen Japan":null,"cher Asia":null,"K\u00f6cher Asia":null},"LeWi_100":{"cher Fall":9.0,"tungen Asia":21.0,"tungen Japan":18.0,"K\u00f6cher Fall":null,"T\u00f6tungen Asia":null,"T\u00f6tungen Japan":null,"cher Asia":null,"K\u00f6cher Asia":null},"Livgo":{"cher Fall":14.0,"tungen Asia":23.0,"tungen Japan":17.0,"K\u00f6cher Fall":null,"T\u00f6tungen Asia":null,"T\u00f6tungen Japan":null,"cher Asia":null,"K\u00f6cher Asia":null},"lizsyy":{"cher Fall":null,"tungen Asia":null,"tungen Japan":null,"K\u00f6cher Fall":24.0,"T\u00f6tungen Asia":26.0,"T\u00f6tungen Japan":29.0,"cher Asia":null,"K\u00f6cher Asia":null},"LordAlexos":{"cher Fall":26.0,"tungen Asia":25.0,"tungen Japan":23.0,"K\u00f6cher Fall":null,"T\u00f6tungen Asia":null,"T\u00f6tungen Japan":null,"cher Asia":null,"K\u00f6cher Asia":null},"Lubotter2009":{"cher Fall":18.0,"tungen Asia":26.0,"tungen Japan":23.0,"K\u00f6cher Fall":null,"T\u00f6tungen Asia":null,"T\u00f6tungen Japan":null,"cher Asia":null,"K\u00f6cher Asia":null},"Luis_XYZ":{"cher Fall":11.0,"tungen Asia":22.0,"tungen Japan":28.0,"K\u00f6cher Fall":null,"T\u00f6tungen Asia":null,"T\u00f6tungen Japan":null,"cher Asia":null,"K\u00f6cher Asia":null},"marbrueck":{"cher Fall":null,"tungen Asia":null,"tungen Japan":null,"K\u00f6cher Fall":12.0,"T\u00f6tungen Asia":23.0,"T\u00f6tungen Japan":23.0,"cher Asia":null,"K\u00f6cher Asia":null},"Martomias":{"cher Fall":17.0,"tungen Asia":26.0,"tungen Japan":23.0,"K\u00f6cher Fall":null,"T\u00f6tungen Asia":null,"T\u00f6tungen Japan":null,"cher Asia":null,"K\u00f6cher Asia":null},"Mincheeen":{"cher Fall":17.0,"tungen Asia":19.0,"tungen Japan":18.0,"K\u00f6cher Fall":null,"T\u00f6tungen Asia":null,"T\u00f6tungen Japan":null,"cher Asia":null,"K\u00f6cher Asia":null},"MrNulfred":{"cher Fall":null,"tungen Asia":null,"tungen Japan":null,"K\u00f6cher Fall":12.0,"T\u00f6tungen Asia":23.0,"T\u00f6tungen Japan":19.0,"cher Asia":null,"K\u00f6cher Asia":null},"Nexilus":{"cher Fall":19.0,"tungen Asia":20.0,"tungen Japan":22.0,"K\u00f6cher Fall":null,"T\u00f6tungen Asia":null,"T\u00f6tungen Japan":null,"cher Asia":null,"K\u00f6cher Asia":null},"Ninivee":{"cher Fall":null,"tungen Asia":null,"tungen Japan":null,"K\u00f6cher Fall":17.0,"T\u00f6tungen Asia":24.0,"T\u00f6tungen Japan":24.0,"cher Asia":null,"K\u00f6cher Asia":null},"officialryzon":{"cher Fall":15.0,"tungen Asia":28.0,"tungen Japan":25.0,"K\u00f6cher Fall":null,"T\u00f6tungen Asia":null,"T\u00f6tungen Japan":null,"cher Asia":null,"K\u00f6cher Asia":null},"Oronor":{"cher Fall":12.0,"tungen Asia":28.0,"tungen Japan":26.0,"K\u00f6cher Fall":null,"T\u00f6tungen Asia":null,"T\u00f6tungen Japan":null,"cher Asia":null,"K\u00f6cher Asia":null},"PedroZockt":{"cher Fall":null,"tungen Asia":null,"tungen Japan":null,"K\u00f6cher Fall":17.0,"T\u00f6tungen Asia":27.0,"T\u00f6tungen Japan":28.0,"cher Asia":null,"K\u00f6cher Asia":null},"Picutar":{"cher Fall":17.0,"tungen Asia":25.0,"tungen Japan":18.0,"K\u00f6cher Fall":null,"T\u00f6tungen Asia":null,"T\u00f6tungen Japan":null,"cher Asia":null,"K\u00f6cher Asia":null},"PixlNight":{"cher Fall":12.0,"tungen Asia":23.0,"tungen Japan":23.0,"K\u00f6cher Fall":null,"T\u00f6tungen Asia":null,"T\u00f6tungen Japan":null,"cher Asia":null,"K\u00f6cher Asia":null},"PolizeiDreamy":{"cher Fall":16.0,"tungen Asia":29.0,"tungen Japan":25.0,"K\u00f6cher Fall":null,"T\u00f6tungen Asia":null,"T\u00f6tungen Japan":null,"cher Asia":null,"K\u00f6cher Asia":null},"Radattel":{"cher Fall":10.0,"tungen Asia":23.0,"tungen Japan":21.0,"K\u00f6cher Fall":null,"T\u00f6tungen Asia":null,"T\u00f6tungen Japan":null,"cher Asia":null,"K\u00f6cher Asia":null},"Raefinzs":{"cher Fall":null,"tungen Asia":null,"tungen Japan":null,"K\u00f6cher Fall":16.0,"T\u00f6tungen Asia":23.0,"T\u00f6tungen Japan":22.0,"cher Asia":null,"K\u00f6cher Asia":null},"Ritokii":{"cher Fall":11.0,"tungen Asia":30.0,"tungen Japan":28.0,"K\u00f6cher Fall":null,"T\u00f6tungen Asia":null,"T\u00f6tungen Japan":null,"cher Asia":null,"K\u00f6cher Asia":null},"rXzEr_Justin":{"cher Fall":13.0,"tungen Asia":19.0,"tungen Japan":29.0,"K\u00f6cher Fall":null,"T\u00f6tungen Asia":null,"T\u00f6tungen Japan":null,"cher Asia":null,"K\u00f6cher Asia":null},"Sackkerl":{"cher Fall":15.0,"tungen Asia":24.0,"tungen Japan":26.0,"K\u00f6cher Fall":null,"T\u00f6tungen Asia":null,"T\u00f6tungen Japan":null,"cher Asia":null,"K\u00f6cher Asia":null},"schmaarek":{"cher Fall":null,"tungen Asia":null,"tungen Japan":null,"K\u00f6cher Fall":19.0,"T\u00f6tungen Asia":27.0,"T\u00f6tungen Japan":25.0,"cher Asia":null,"K\u00f6cher Asia":null},"Sebi1801":{"cher Fall":2.0,"tungen Asia":23.0,"tungen Japan":22.0,"K\u00f6cher Fall":null,"T\u00f6tungen Asia":null,"T\u00f6tungen Japan":null,"cher Asia":null,"K\u00f6cher Asia":null},"Seemops_8":{"cher Fall":null,"tungen Asia":null,"tungen Japan":null,"K\u00f6cher Fall":17.0,"T\u00f6tungen Asia":24.0,"T\u00f6tungen Japan":33.0,"cher Asia":null,"K\u00f6cher Asia":null},"Sey__":{"cher Fall":null,"tungen Asia":null,"tungen Japan":null,"K\u00f6cher Fall":19.0,"T\u00f6tungen Asia":26.0,"T\u00f6tungen Japan":23.0,"cher Asia":null,"K\u00f6cher Asia":null},"SpeckyCut":{"cher Fall":16.0,"tungen Asia":17.0,"tungen Japan":19.0,"K\u00f6cher Fall":null,"T\u00f6tungen Asia":null,"T\u00f6tungen Japan":null,"cher Asia":null,"K\u00f6cher Asia":null},"StaudammAusHolz":{"cher Fall":18.0,"tungen Asia":19.0,"tungen Japan":20.0,"K\u00f6cher Fall":null,"T\u00f6tungen Asia":null,"T\u00f6tungen Japan":null,"cher Asia":null,"K\u00f6cher Asia":null},"Tomiokey":{"cher Fall":24.0,"tungen Asia":26.0,"tungen Japan":25.0,"K\u00f6cher Fall":null,"T\u00f6tungen Asia":null,"T\u00f6tungen Japan":null,"cher Asia":null,"K\u00f6cher Asia":null},"tsuneee":{"cher Fall":null,"tungen Asia":null,"tungen Japan":null,"K\u00f6cher Fall":23.0,"T\u00f6tungen Asia":27.0,"T\u00f6tungen Japan":30.0,"cher Asia":null,"K\u00f6cher Asia":null},"twitchparaskiill":{"cher Fall":null,"tungen Asia":null,"tungen Japan":28.0,"K\u00f6cher Fall":null,"T\u00f6tungen Asia":null,"T\u00f6tungen Japan":null,"cher Asia":27.0,"K\u00f6cher Asia":null},"Umgfoin":{"cher Fall":null,"tungen Asia":null,"tungen Japan":null,"K\u00f6cher Fall":18.0,"T\u00f6tungen Asia":21.0,"T\u00f6tungen Japan":28.0,"cher Asia":null,"K\u00f6cher Asia":null},"WirdNichtGeladen":{"cher Fall":16.0,"tungen Asia":20.0,"tungen Japan":21.0,"K\u00f6cher Fall":null,"T\u00f6tungen Asia":null,"T\u00f6tungen Japan":null,"cher Asia":null,"K\u00f6cher Asia":null},"Wissender":{"cher Fall":14.0,"tungen Asia":21.0,"tungen Japan":22.0,"K\u00f6cher Fall":null,"T\u00f6tungen Asia":null,"T\u00f6tungen Japan":null,"cher Asia":null,"K\u00f6cher Asia":null},"xBaumeisterin":{"cher Fall":9.0,"tungen Asia":19.0,"tungen Japan":18.0,"K\u00f6cher Fall":null,"T\u00f6tungen Asia":null,"T\u00f6tungen Japan":null,"cher Asia":null,"K\u00f6cher Asia":null},"xX_Dima_ggg_Xx6":{"cher Fall":null,"tungen Asia":null,"tungen Japan":null,"K\u00f6cher Fall":18.0,"T\u00f6tungen Asia":26.0,"T\u00f6tungen Japan":22.0,"cher Asia":null,"K\u00f6cher Asia":null},"xX_Masha_ggg_Xx9":{"cher Fall":null,"tungen Asia":null,"tungen Japan":null,"K\u00f6cher Fall":12.0,"T\u00f6tungen Asia":23.0,"T\u00f6tungen Japan":18.0,"cher Asia":null,"K\u00f6cher Asia":null},"ymq_":{"cher Fall":null,"tungen Asia":null,"tungen Japan":null,"K\u00f6cher Fall":21.0,"T\u00f6tungen Asia":28.0,"T\u00f6tungen Japan":26.0,"cher Asia":null,"K\u00f6cher Asia":null},"yzvm":{"cher Fall":null,"tungen Asia":null,"tungen Japan":null,"K\u00f6cher Fall":17.0,"T\u00f6tungen Asia":29.0,"T\u00f6tungen Japan":26.0,"cher Asia":null,"K\u00f6cher Asia":null},"zTotito":{"cher Fall":18.0,"tungen Asia":21.0,"tungen Japan":22.0,"K\u00f6cher Fall":null,"T\u00f6tungen Asia":null,"T\u00f6tungen Japan":null,"cher Asia":null,"K\u00f6cher Asia":null},"_n3d":{"cher Fall":18.0,"tungen Asia":28.0,"tungen Japan":31.0,"K\u00f6cher Fall":null,"T\u00f6tungen Asia":null,"T\u00f6tungen Japan":null,"cher Asia":null,"K\u00f6cher Asia":null},"_Waldi_":{"cher Fall":15.0,"tungen Asia":27.0,"tungen Japan":22.0,"K\u00f6cher Fall":null,"T\u00f6tungen Asia":null,"T\u00f6tungen Japan":null,"cher Asia":null,"K\u00f6cher Asia":null}}