{"SpeckyCut":{"Desert":25.215,"Ice Cave":null,"Nether":25.697},"demiu":{"Desert":null,"Ice Cave":null,"Nether":null},"_n3d":{"Desert":24.782,"Ice Cave":29.991,"Nether":25.064},"Sebi1801":{"Desert":24.624,"Ice Cave":null,"Nether":25.271},"Wissender":{"Desert":24.545,"Ice Cave":null,"Nether":24.233},"Gryzes":{"Desert":26.383,"Ice Cave":38.848,"Nether":26.998},"Gobo9":{"Desert":24.147,"Ice Cave":35.535,"Nether":24.677},"Anni808":{"Desert":27.807,"Ice Cave":null,"Nether":26.34},"LeWi_100":{"Desert":23.767,"Ice Cave":40.364,"Nether":24.879},"_Waldi_":{"Desert":25.108,"Ice Cave":32.755,"Nether":26.397},"Grapfen":{"Desert":24.178,"Ice Cave":31.29,"Nether":24.915},"PixlNight":{"Desert":23.792,"Ice Cave":null,"Nether":25.414},"agowskyy":{"Desert":26.825,"Ice Cave":null,"Nether":26.435},"TheBreadHD":{"Desert":26.404,"Ice Cave":52.108,"Nether":27.558},"Axollotel":{"Desert":24.6,"Ice Cave":null,"Nether":25.991},"T_Niko_T":{"Desert":27.123,"Ice Cave":null,"Nether":27.194},"yzvm":{"Desert":25.4,"Ice Cave":null,"Nether":25.097},"xBaumeisterin":{"Desert":24.633,"Ice Cave":null,"Nether":24.887},"Ninivee":{"Desert":25.74,"Ice Cave":28.571,"Nether":25.492},"Tomiokey":{"Desert":25.212,"Ice Cave":null,"Nether":26.119},"DerAutist":{"Desert":null,"Ice Cave":null,"Nether":null},"PolizeiDreamy":{"Desert":25.158,"Ice Cave":null,"Nether":25.796},"xX_Dima_ggg_Xx6":{"Desert":25.308,"Ice Cave":40.656,"Nether":26.139},"Radattel":{"Desert":25.383,"Ice Cave":null,"Nether":25.817},"DerBaumIstDerWeg":{"Desert":24.201,"Ice Cave":null,"Nether":25.358},"Falke23_5":{"Desert":25.392,"Ice Cave":null,"Nether":25.371},"TheFabo":{"Desert":24.271,"Ice Cave":null,"Nether":24.593},"DieserBear":{"Desert":24.416,"Ice Cave":null,"Nether":24.613},"Picutar":{"Desert":25.409,"Ice Cave":null,"Nether":26.05},"2B9":{"Desert":24.365,"Ice Cave":null,"Nether":23.949},"HerrDante":{"Desert":23.81,"Ice Cave":null,"Nether":23.774},"KakaMC":{"Desert":24.607,"Ice Cave":null,"Nether":24.858},"StaudammAusHolz":{"Desert":26.504,"Ice Cave":null,"Nether":25.47},"Kyuudo":{"Desert":25.342,"Ice Cave":null,"Nether":25.797},"twitchparaskiill":{"Desert":25.92,"Ice Cave":null,"Nether":24.709},"Sey__":{"Desert":24.539,"Ice Cave":28.814,"Nether":24.112},"Radiokopf":{"Desert":27.169,"Ice Cave":47.092,"Nether":26.89},"ForceFox":{"Desert":27.579,"Ice Cave":53.533,"Nether":27.747},"zBro":{"Desert":23.716,"Ice Cave":null,"Nether":23.756},"Harold_Sensemann":{"Desert":24.933,"Ice Cave":70.589,"Nether":25.438},"Pedrozockt":{"Desert":24.297,"Ice Cave":30.357,"Nether":24.492},"MrNulfred":{"Desert":26.502,"Ice Cave":null,"Nether":25.656},"Kopfradio":{"Desert":28.779,"Ice Cave":null,"Nether":29.999},"loukrativ":{"Desert":41.467,"Ice Cave":42.726,"Nether":39.035},"M0osebumps":{"Desert":25.163,"Ice Cave":null,"Nether":24.363},"Kokochampo":{"Desert":26.876,"Ice Cave":null,"Nether":26.969},"JennieKim":{"Desert":25.573,"Ice Cave":null,"Nether":26.861},"Umgfoin":{"Desert":25.87,"Ice Cave":33.296,"Nether":24.96},"ffawks":{"Desert":25.544,"Ice Cave":32.382,"Nether":25.323},"byTobi":{"Desert":24.429,"Ice Cave":null,"Nether":25.794},"Shiewk":{"Desert":26.207,"Ice Cave":42.001,"Nether":27.015},"La_meleagro":{"Desert":26.188,"Ice Cave":null,"Nether":25.713},"DarkCobweb":{"Desert":24.648,"Ice Cave":null,"Nether":24.802},"Sackkerl":{"Desert":25.555,"Ice Cave":null,"Nether":25.75},"Gerrygames":{"Desert":24.229,"Ice Cave":null,"Nether":24.486},"BusinessBent":{"Desert":24.529,"Ice Cave":43.898,"Nether":25.922},"Txlentierter":{"Desert":null,"Ice Cave":null,"Nether":27.628},"Luis_XYZ":{"Desert":24.605,"Ice Cave":30.113,"Nether":30.002},"Oronor":{"Desert":24.555,"Ice Cave":null,"Nether":24.066},"GamemasterNiki":{"Desert":26.365,"Ice Cave":49.814,"Nether":26.64},"LordAlexos":{"Desert":25.826,"Ice Cave":null,"Nether":26.021},"GrafikKatze":{"Desert":25.96,"Ice Cave":null,"Nether":27.979},"cediiiiii_10":{"Desert":23.83,"Ice Cave":null,"Nether":24.446},"Dokkkkko":{"Desert":26.45,"Ice Cave":null,"Nether":27.552},"deadfiight":{"Desert":24.513,"Ice Cave":29.561,"Nether":26.164},"Kanickelul":{"Desert":27.464,"Ice Cave":null,"Nether":26.666},"crocodile1870":{"Desert":25.557,"Ice Cave":47.654,"Nether":24.838},"Sower_":{"Desert":26.872,"Ice Cave":null,"Nether":25.999},"Kokochampi":{"Desert":26.798,"Ice Cave":null,"Nether":29.588},"yiiq":{"Desert":24.243,"Ice Cave":36.268,"Nether":24.458},"Snitcherella":{"Desert":24.21,"Ice Cave":null,"Nether":25.405},"Keenaai":{"Desert":26.147,"Ice Cave":34.646,"Nether":25.515},"ReichesBrot":{"Desert":25.016,"Ice Cave":27.889,"Nether":24.545},"lolisamasan":{"Desert":25.322,"Ice Cave":32.6,"Nether":26.163},"Raefinzs":{"Desert":28.16,"Ice Cave":null,"Nether":29.009},"ByNetherdude":{"Desert":29.339,"Ice Cave":55.99,"Nether":26.902},"frutigall":{"Desert":24.592,"Ice Cave":null,"Nether":24.145},"Joy_8oy":{"Desert":26.618,"Ice Cave":null,"Nether":26.412},"CML_Justin":{"Desert":24.956,"Ice Cave":31.739,"Nether":25.579},"Gummibearchen":{"Desert":24.87,"Ice Cave":35.147,"Nether":24.726},"officialryzon":{"Desert":30.844,"Ice Cave":null,"Nether":31.055},"h4nnes":{"Desert":25.789,"Ice Cave":32.935,"Nether":25.037},"Krusti":{"Desert":24.318,"Ice Cave":null,"Nether":24.121},"marbrueck":{"Desert":26.084,"Ice Cave":38.541,"Nether":26.139},"Vacted":{"Desert":27.348,"Ice Cave":38.627,"Nether":26.367},"Janne4k":{"Desert":30.898,"Ice Cave":39.233,"Nether":28.441},"Bartschii":{"Desert":52.12,"Ice Cave":null,"Nether":29.314},"SB387":{"Desert":25.951,"Ice Cave":null,"Nether":25.656},"JOW23":{"Desert":23.931,"Ice Cave":null,"Nether":24.556},"Ritokii":{"Desert":24.248,"Ice Cave":38.148,"Nether":24.235},"lvlaurin":{"Desert":25.895,"Ice Cave":41.452,"Nether":30.965},"GeneralEnte06":{"Desert":24.457,"Ice Cave":44.866,"Nether":25.651},"revolverz":{"Desert":27.174,"Ice Cave":null,"Nether":34.064},"ScreamingBlatz":{"Desert":26.883,"Ice Cave":53.784,"Nether":25.422},"M0orey_0":{"Desert":24.059,"Ice Cave":35.303,"Nether":25.242},"Mincheeen":{"Desert":24.756,"Ice Cave":42.711,"Nether":25.393},"2wc":{"Desert":null,"Ice Cave":null,"Nether":null},"H1ghsay":{"Desert":24.994,"Ice Cave":null,"Nether":25.841},"Feinberg":{"Desert":26.102,"Ice Cave":null,"Nether":27.192},"Navex":{"Desert":29.359,"Ice Cave":45.408,"Nether":31.28},"SiLoHB":{"Desert":35.621,"Ice Cave":38.987,"Nether":30.44},"Morittz":{"Desert":24.617,"Ice Cave":null,"Nether":25.078},"cxl1lo":{"Desert":28.224,"Ice Cave":null,"Nether":28.128},"LeMetin_":{"Desert":23.682,"Ice Cave":28.956,"Nether":24.235},"unausgesprochen":{"Desert":24.192,"Ice Cave":null,"Nether":24.491},"Freeeedom":{"Desert":24.104,"Ice Cave":42.133,"Nether":25.402},"miridis41":{"Desert":24.759,"Ice Cave":null,"Nether":24.76},"Lingex":{"Desert":28.329,"Ice Cave":34.12,"Nether":29.75},"xX_Masha_ggg_Xx9":{"Desert":31.325,"Ice Cave":null,"Nether":30.253},"lizsyy":{"Desert":25.355,"Ice Cave":40.261,"Nether":24.903},"camman18YT":{"Desert":24.782,"Ice Cave":31.923,"Nether":25.426},"Jan2220":{"Desert":25.115,"Ice Cave":31.523,"Nether":25.17},"Davinci_Son":{"Desert":24.044,"Ice Cave":null,"Nether":24.243},"Flitzi_Dino":{"Desert":42.88,"Ice Cave":null,"Nether":42.655},"Nexilus":{"Desert":24.519,"Ice Cave":50.833,"Nether":26.905},"Seemops_8":{"Desert":25.681,"Ice Cave":36.366,"Nether":25.622},"chrisihalt":{"Desert":25.371,"Ice Cave":23.751,"Nether":24.872},"Allooy":{"Desert":24.42,"Ice Cave":null,"Nether":25.69},"Chander24":{"Desert":29.354,"Ice Cave":null,"Nether":27.509},"Fflopse":{"Desert":24.806,"Ice Cave":32.427,"Nether":23.706},"bawskey":{"Desert":25.424,"Ice Cave":null,"Nether":26.842},"WirdNichtGeladen":{"Desert":24.992,"Ice Cave":null,"Nether":26.178},"HeIsJustAPoorBoy":{"Desert":24.192,"Ice Cave":33.711,"Nether":25.047},"Ex4cted":{"Desert":24.253,"Ice Cave":33.468,"Nether":24.128},"Mvsk_":{"Desert":27.197,"Ice Cave":33.64,"Nether":27.047},"juvona":{"Desert":44.692,"Ice Cave":48.368,"Nether":28.28},"jimmi1410":{"Desert":24.659,"Ice Cave":null,"Nether":27.05},"Lubottus":{"Desert":25.844,"Ice Cave":39.358,"Nether":24.939},"lolisamakun":{"Desert":26.706,"Ice Cave":37.142,"Nether":25.941},"Martomias":{"Desert":26.156,"Ice Cave":null,"Nether":25.194},"20LeRe10":{"Desert":28.497,"Ice Cave":42.994,"Nether":26.979}}