{"20LeRe10":{"Garden":3.0,"Grass":null,"T\u00f6tung Grass":null,"T\u00f6tungen Grass":5.0,"T\u00f6tungen Vulcano":4.0,"Vulcano":null,"tungen Grass":null,"tungen Vulcano":null},"agowskyy":{"Garden":11.0,"Grass":null,"T\u00f6tung Grass":null,"T\u00f6tungen Grass":5.0,"T\u00f6tungen Vulcano":7.0,"Vulcano":null,"tungen Grass":null,"tungen Vulcano":null},"Anni808":{"Garden":5.0,"Grass":null,"T\u00f6tung Grass":null,"T\u00f6tungen Grass":3.0,"T\u00f6tungen Vulcano":5.0,"Vulcano":null,"tungen Grass":null,"tungen Vulcano":null},"Axollotel":{"Garden":8.0,"Grass":null,"T\u00f6tung Grass":null,"T\u00f6tungen Grass":4.0,"T\u00f6tungen Vulcano":7.0,"Vulcano":null,"tungen Grass":null,"tungen Vulcano":null},"BacardiSprite":{"Garden":10.0,"Grass":null,"T\u00f6tung Grass":null,"T\u00f6tungen Grass":4.0,"T\u00f6tungen Vulcano":6.0,"Vulcano":null,"tungen Grass":null,"tungen Vulcano":null},"bawskey":{"Garden":6.0,"Grass":null,"T\u00f6tung Grass":null,"T\u00f6tungen Grass":5.0,"T\u00f6tungen Vulcano":11.0,"Vulcano":null,"tungen Grass":null,"tungen Vulcano":null},"BusinessBent":{"Garden":6.0,"Grass":null,"T\u00f6tung Grass":null,"T\u00f6tungen Grass":6.0,"T\u00f6tungen Vulcano":7.0,"Vulcano":null,"tungen Grass":null,"tungen Vulcano":null},"ByNetherdude":{"Garden":5.0,"Grass":null,"T\u00f6tung Grass":null,"T\u00f6tungen Grass":5.0,"T\u00f6tungen Vulcano":5.0,"Vulcano":null,"tungen Grass":null,"tungen Vulcano":null},"byTobi":{"Garden":11.0,"Grass":null,"T\u00f6tung Grass":null,"T\u00f6tungen Grass":9.0,"T\u00f6tungen Vulcano":9.0,"Vulcano":null,"tungen Grass":null,"tungen Vulcano":null},"cediiiiii_10":{"Garden":12.0,"Grass":null,"T\u00f6tung Grass":null,"T\u00f6tungen Grass":12.0,"T\u00f6tungen Vulcano":12.0,"Vulcano":null,"tungen Grass":null,"tungen Vulcano":null},"Chander24":{"Garden":4.0,"Grass":null,"T\u00f6tung Grass":null,"T\u00f6tungen Grass":4.0,"T\u00f6tungen Vulcano":3.0,"Vulcano":null,"tungen Grass":null,"tungen Vulcano":null},"Chrisi20101":{"Garden":6.0,"Grass":null,"T\u00f6tung Grass":null,"T\u00f6tungen Grass":6.0,"T\u00f6tungen Vulcano":8.0,"Vulcano":null,"tungen Grass":null,"tungen Vulcano":null},"crocodile1870":{"Garden":6.0,"Grass":null,"T\u00f6tung Grass":null,"T\u00f6tungen Grass":4.0,"T\u00f6tungen Vulcano":7.0,"Vulcano":null,"tungen Grass":null,"tungen Vulcano":null},"cxl1lo":{"Garden":4.0,"Grass":null,"T\u00f6tung Grass":null,"T\u00f6tungen Grass":5.0,"T\u00f6tungen Vulcano":6.0,"Vulcano":null,"tungen Grass":null,"tungen Vulcano":null},"DarkCobweb":{"Garden":12.0,"Grass":null,"T\u00f6tung Grass":null,"T\u00f6tungen Grass":12.0,"T\u00f6tungen Vulcano":6.0,"Vulcano":null,"tungen Grass":null,"tungen Vulcano":null},"deadfiight":{"Garden":8.0,"Grass":null,"T\u00f6tung Grass":null,"T\u00f6tungen Grass":8.0,"T\u00f6tungen Vulcano":6.0,"Vulcano":null,"tungen Grass":null,"tungen Vulcano":null},"DerBaumIstDerWeg":{"Garden":5.0,"Grass":null,"T\u00f6tung Grass":null,"T\u00f6tungen Grass":5.0,"T\u00f6tungen Vulcano":7.0,"Vulcano":null,"tungen Grass":null,"tungen Vulcano":null},"Dokkkkko":{"Garden":5.0,"Grass":null,"T\u00f6tung Grass":null,"T\u00f6tungen Grass":11.0,"T\u00f6tungen Vulcano":6.0,"Vulcano":null,"tungen Grass":null,"tungen Vulcano":null},"Ex4cted":{"Garden":9.0,"Grass":null,"T\u00f6tung Grass":null,"T\u00f6tungen Grass":8.0,"T\u00f6tungen Vulcano":9.0,"Vulcano":null,"tungen Grass":null,"tungen Vulcano":null},"Falke23_5":{"Garden":10.0,"Grass":null,"T\u00f6tung Grass":null,"T\u00f6tungen Grass":10.0,"T\u00f6tungen Vulcano":5.0,"Vulcano":null,"tungen Grass":null,"tungen Vulcano":null},"Feinberg":{"Garden":4.0,"Grass":null,"T\u00f6tung Grass":null,"T\u00f6tungen Grass":3.0,"T\u00f6tungen Vulcano":null,"Vulcano":null,"tungen Grass":null,"tungen Vulcano":null},"Fflopse":{"Garden":9.0,"Grass":null,"T\u00f6tung Grass":null,"T\u00f6tungen Grass":10.0,"T\u00f6tungen Vulcano":14.0,"Vulcano":null,"tungen Grass":null,"tungen Vulcano":null},"ForceFox":{"Garden":7.0,"Grass":null,"T\u00f6tung Grass":null,"T\u00f6tungen Grass":7.0,"T\u00f6tungen Vulcano":7.0,"Vulcano":null,"tungen Grass":null,"tungen Vulcano":null},"Freeeedom":{"Garden":6.0,"Grass":null,"T\u00f6tung Grass":null,"T\u00f6tungen Grass":9.0,"T\u00f6tungen Vulcano":9.0,"Vulcano":null,"tungen Grass":null,"tungen Vulcano":null},"frutigall":{"Garden":8.0,"Grass":null,"T\u00f6tung Grass":null,"T\u00f6tungen Grass":9.0,"T\u00f6tungen Vulcano":9.0,"Vulcano":null,"tungen Grass":null,"tungen Vulcano":null},"GamemasterNiki":{"Garden":8.0,"Grass":null,"T\u00f6tung Grass":null,"T\u00f6tungen Grass":5.0,"T\u00f6tungen Vulcano":9.0,"Vulcano":null,"tungen Grass":null,"tungen Vulcano":null},"GeneralEnte06":{"Garden":7.0,"Grass":null,"T\u00f6tung Grass":null,"T\u00f6tungen Grass":7.0,"T\u00f6tungen Vulcano":8.0,"Vulcano":null,"tungen Grass":null,"tungen Vulcano":null},"Gerrygames":{"Garden":5.0,"Grass":null,"T\u00f6tung Grass":null,"T\u00f6tungen Grass":7.0,"T\u00f6tungen Vulcano":null,"Vulcano":null,"tungen Grass":null,"tungen Vulcano":null},"Gobo9":{"Garden":10.0,"Grass":null,"T\u00f6tung Grass":null,"T\u00f6tungen Grass":11.0,"T\u00f6tungen Vulcano":10.0,"Vulcano":null,"tungen Grass":null,"tungen Vulcano":null},"GrafikKatze":{"Garden":8.0,"Grass":null,"T\u00f6tung Grass":null,"T\u00f6tungen Grass":8.0,"T\u00f6tungen Vulcano":3.0,"Vulcano":null,"tungen Grass":null,"tungen Vulcano":null},"Grapfen":{"Garden":12.0,"Grass":null,"T\u00f6tung Grass":null,"T\u00f6tungen Grass":10.0,"T\u00f6tungen Vulcano":10.0,"Vulcano":null,"tungen Grass":null,"tungen Vulcano":null},"Gummibearchen":{"Garden":9.0,"Grass":null,"T\u00f6tung Grass":null,"T\u00f6tungen Grass":8.0,"T\u00f6tungen Vulcano":12.0,"Vulcano":null,"tungen Grass":null,"tungen Vulcano":null},"H1ghsay":{"Garden":5.0,"Grass":null,"T\u00f6tung Grass":null,"T\u00f6tungen Grass":7.0,"T\u00f6tungen Vulcano":6.0,"Vulcano":null,"tungen Grass":null,"tungen Vulcano":null},"h4nnes":{"Garden":10.0,"Grass":null,"T\u00f6tung Grass":null,"T\u00f6tungen Grass":9.0,"T\u00f6tungen Vulcano":8.0,"Vulcano":null,"tungen Grass":null,"tungen Vulcano":null},"Harold_Sensemann":{"Garden":8.0,"Grass":null,"T\u00f6tung Grass":null,"T\u00f6tungen Grass":8.0,"T\u00f6tungen Vulcano":4.0,"Vulcano":null,"tungen Grass":null,"tungen Vulcano":null},"HerrDante":{"Garden":10.0,"Grass":null,"T\u00f6tung Grass":null,"T\u00f6tungen Grass":9.0,"T\u00f6tungen Vulcano":9.0,"Vulcano":null,"tungen Grass":null,"tungen Vulcano":null},"Jan2220":{"Garden":8.0,"Grass":null,"T\u00f6tung Grass":null,"T\u00f6tungen Grass":6.0,"T\u00f6tungen Vulcano":7.0,"Vulcano":null,"tungen Grass":null,"tungen Vulcano":null},"JennieKim":{"Garden":6.0,"Grass":null,"T\u00f6tung Grass":null,"T\u00f6tungen Grass":8.0,"T\u00f6tungen Vulcano":7.0,"Vulcano":null,"tungen Grass":null,"tungen Vulcano":null},"jimmi1410":{"Garden":3.0,"Grass":null,"T\u00f6tung Grass":null,"T\u00f6tungen Grass":3.0,"T\u00f6tungen Vulcano":8.0,"Vulcano":null,"tungen Grass":null,"tungen Vulcano":null},"JOW23":{"Garden":12.0,"Grass":null,"T\u00f6tung Grass":null,"T\u00f6tungen Grass":9.0,"T\u00f6tungen Vulcano":9.0,"Vulcano":null,"tungen Grass":null,"tungen Vulcano":null},"Joy_8oy":{"Garden":3.0,"Grass":null,"T\u00f6tung Grass":null,"T\u00f6tungen Grass":5.0,"T\u00f6tungen Vulcano":5.0,"Vulcano":null,"tungen Grass":null,"tungen Vulcano":null},"JustK1lling":{"Garden":5.0,"Grass":null,"T\u00f6tung Grass":null,"T\u00f6tungen Grass":1.0,"T\u00f6tungen Vulcano":4.0,"Vulcano":null,"tungen Grass":null,"tungen Vulcano":null},"KakaMC":{"Garden":12.0,"Grass":null,"T\u00f6tung Grass":null,"T\u00f6tungen Grass":7.0,"T\u00f6tungen Vulcano":8.0,"Vulcano":null,"tungen Grass":null,"tungen Vulcano":null},"Kanickelul":{"Garden":1.0,"Grass":null,"T\u00f6tung Grass":3.0,"T\u00f6tungen Grass":null,"T\u00f6tungen Vulcano":null,"Vulcano":null,"tungen Grass":null,"tungen Vulcano":null},"Kokochampi":{"Garden":4.0,"Grass":null,"T\u00f6tung Grass":null,"T\u00f6tungen Grass":7.0,"T\u00f6tungen Vulcano":2.0,"Vulcano":null,"tungen Grass":null,"tungen Vulcano":null},"Kokochampo":{"Garden":4.0,"Grass":null,"T\u00f6tung Grass":null,"T\u00f6tungen Grass":7.0,"T\u00f6tungen Vulcano":5.0,"Vulcano":null,"tungen Grass":null,"tungen Vulcano":null},"Krusti":{"Garden":10.0,"Grass":null,"T\u00f6tung Grass":null,"T\u00f6tungen Grass":9.0,"T\u00f6tungen Vulcano":8.0,"Vulcano":null,"tungen Grass":null,"tungen Vulcano":null},"Kyuudo":{"Garden":7.0,"Grass":null,"T\u00f6tung Grass":null,"T\u00f6tungen Grass":8.0,"T\u00f6tungen Vulcano":8.0,"Vulcano":null,"tungen Grass":null,"tungen Vulcano":null},"LeWi_100":{"Garden":7.0,"Grass":null,"T\u00f6tung Grass":null,"T\u00f6tungen Grass":6.0,"T\u00f6tungen Vulcano":6.0,"Vulcano":null,"tungen Grass":null,"tungen Vulcano":null},"Livgo":{"Garden":7.0,"Grass":null,"T\u00f6tung Grass":null,"T\u00f6tungen Grass":null,"T\u00f6tungen Vulcano":null,"Vulcano":null,"tungen Grass":7.0,"tungen Vulcano":7.0},"lizsyy":{"Garden":6.0,"Grass":null,"T\u00f6tung Grass":null,"T\u00f6tungen Grass":8.0,"T\u00f6tungen Vulcano":8.0,"Vulcano":null,"tungen Grass":null,"tungen Vulcano":null},"LordAlexos":{"Garden":8.0,"Grass":null,"T\u00f6tung Grass":null,"T\u00f6tungen Grass":7.0,"T\u00f6tungen Vulcano":8.0,"Vulcano":null,"tungen Grass":null,"tungen Vulcano":null},"Lubotter2009":{"Garden":6.0,"Grass":null,"T\u00f6tung Grass":null,"T\u00f6tungen Grass":null,"T\u00f6tungen Vulcano":null,"Vulcano":null,"tungen Grass":7.0,"tungen Vulcano":10.0},"Luis_XYZ":{"Garden":7.0,"Grass":null,"T\u00f6tung Grass":null,"T\u00f6tungen Grass":4.0,"T\u00f6tungen Vulcano":8.0,"Vulcano":null,"tungen Grass":null,"tungen Vulcano":null},"M0orey_0":{"Garden":7.0,"Grass":null,"T\u00f6tung Grass":null,"T\u00f6tungen Grass":9.0,"T\u00f6tungen Vulcano":8.0,"Vulcano":null,"tungen Grass":null,"tungen Vulcano":null},"marbrueck":{"Garden":8.0,"Grass":null,"T\u00f6tung Grass":null,"T\u00f6tungen Grass":8.0,"T\u00f6tungen Vulcano":7.0,"Vulcano":null,"tungen Grass":null,"tungen Vulcano":null},"Martomias":{"Garden":7.0,"Grass":null,"T\u00f6tung Grass":null,"T\u00f6tungen Grass":7.0,"T\u00f6tungen Vulcano":8.0,"Vulcano":null,"tungen Grass":null,"tungen Vulcano":null},"Mincheeen":{"Garden":5.0,"Grass":null,"T\u00f6tung Grass":null,"T\u00f6tungen Grass":6.0,"T\u00f6tungen Vulcano":6.0,"Vulcano":null,"tungen Grass":null,"tungen Vulcano":null},"MrNulfred":{"Garden":5.0,"Grass":null,"T\u00f6tung Grass":null,"T\u00f6tungen Grass":5.0,"T\u00f6tungen Vulcano":9.0,"Vulcano":null,"tungen Grass":null,"tungen Vulcano":null},"Mvsk_":{"Garden":6.0,"Grass":null,"T\u00f6tung Grass":null,"T\u00f6tungen Grass":5.0,"T\u00f6tungen Vulcano":6.0,"Vulcano":null,"tungen Grass":null,"tungen Vulcano":null},"Nexilus":{"Garden":6.0,"Grass":null,"T\u00f6tung Grass":null,"T\u00f6tungen Grass":7.0,"T\u00f6tungen Vulcano":8.0,"Vulcano":null,"tungen Grass":null,"tungen Vulcano":null},"Ninivee":{"Garden":9.0,"Grass":null,"T\u00f6tung Grass":null,"T\u00f6tungen Grass":11.0,"T\u00f6tungen Vulcano":9.0,"Vulcano":null,"tungen Grass":null,"tungen Vulcano":null},"officialryzon":{"Garden":null,"Grass":null,"T\u00f6tung Grass":null,"T\u00f6tungen Grass":9.0,"T\u00f6tungen Vulcano":null,"Vulcano":8.0,"tungen Grass":null,"tungen Vulcano":null},"Oronor":{"Garden":6.0,"Grass":null,"T\u00f6tung Grass":null,"T\u00f6tungen Grass":6.0,"T\u00f6tungen Vulcano":2.0,"Vulcano":null,"tungen Grass":null,"tungen Vulcano":null},"PedroZockt":{"Garden":10.0,"Grass":null,"T\u00f6tung Grass":null,"T\u00f6tungen Grass":12.0,"T\u00f6tungen Vulcano":11.0,"Vulcano":null,"tungen Grass":null,"tungen Vulcano":null},"Picutar":{"Garden":9.0,"Grass":null,"T\u00f6tung Grass":null,"T\u00f6tungen Grass":5.0,"T\u00f6tungen Vulcano":7.0,"Vulcano":null,"tungen Grass":null,"tungen Vulcano":null},"PixlNight":{"Garden":7.0,"Grass":null,"T\u00f6tung Grass":null,"T\u00f6tungen Grass":6.0,"T\u00f6tungen Vulcano":6.0,"Vulcano":null,"tungen Grass":null,"tungen Vulcano":null},"PolizeiDreamy":{"Garden":6.0,"Grass":null,"T\u00f6tung Grass":null,"T\u00f6tungen Grass":8.0,"T\u00f6tungen Vulcano":4.0,"Vulcano":null,"tungen Grass":null,"tungen Vulcano":null},"Radattel":{"Garden":5.0,"Grass":null,"T\u00f6tung Grass":null,"T\u00f6tungen Grass":6.0,"T\u00f6tungen Vulcano":7.0,"Vulcano":null,"tungen Grass":null,"tungen Vulcano":null},"Raefinzs":{"Garden":5.0,"Grass":null,"T\u00f6tung Grass":null,"T\u00f6tungen Grass":5.0,"T\u00f6tungen Vulcano":5.0,"Vulcano":null,"tungen Grass":null,"tungen Vulcano":null},"Ritokii":{"Garden":9.0,"Grass":null,"T\u00f6tung Grass":null,"T\u00f6tungen Grass":10.0,"T\u00f6tungen Vulcano":6.0,"Vulcano":null,"tungen Grass":null,"tungen Vulcano":null},"rXzEr_Justin":{"Garden":6.0,"Grass":null,"T\u00f6tung Grass":null,"T\u00f6tungen Grass":6.0,"T\u00f6tungen Vulcano":6.0,"Vulcano":null,"tungen Grass":null,"tungen Vulcano":null},"Sackkerl":{"Garden":7.0,"Grass":null,"T\u00f6tung Grass":null,"T\u00f6tungen Grass":7.0,"T\u00f6tungen Vulcano":5.0,"Vulcano":null,"tungen Grass":null,"tungen Vulcano":null},"SB387":{"Garden":7.0,"Grass":null,"T\u00f6tung Grass":null,"T\u00f6tungen Grass":6.0,"T\u00f6tungen Vulcano":4.0,"Vulcano":null,"tungen Grass":null,"tungen Vulcano":null},"schmaarek":{"Garden":9.0,"Grass":null,"T\u00f6tung Grass":null,"T\u00f6tungen Grass":8.0,"T\u00f6tungen Vulcano":9.0,"Vulcano":null,"tungen Grass":null,"tungen Vulcano":null},"ScreamingBlatz":{"Garden":6.0,"Grass":null,"T\u00f6tung Grass":null,"T\u00f6tungen Grass":7.0,"T\u00f6tungen Vulcano":7.0,"Vulcano":null,"tungen Grass":null,"tungen Vulcano":null},"Sebi1801":{"Garden":10.0,"Grass":null,"T\u00f6tung Grass":null,"T\u00f6tungen Grass":8.0,"T\u00f6tungen Vulcano":null,"Vulcano":null,"tungen Grass":null,"tungen Vulcano":null},"Seemops_8":{"Garden":6.0,"Grass":null,"T\u00f6tung Grass":null,"T\u00f6tungen Grass":7.0,"T\u00f6tungen Vulcano":6.0,"Vulcano":null,"tungen Grass":null,"tungen Vulcano":null},"Sey__":{"Garden":8.0,"Grass":null,"T\u00f6tung Grass":null,"T\u00f6tungen Grass":9.0,"T\u00f6tungen Vulcano":7.0,"Vulcano":null,"tungen Grass":null,"tungen Vulcano":null},"Shiewk":{"Garden":7.0,"Grass":null,"T\u00f6tung Grass":null,"T\u00f6tungen Grass":5.0,"T\u00f6tungen Vulcano":7.0,"Vulcano":null,"tungen Grass":null,"tungen Vulcano":null},"Snitcherella":{"Garden":5.0,"Grass":null,"T\u00f6tung Grass":null,"T\u00f6tungen Grass":4.0,"T\u00f6tungen Vulcano":7.0,"Vulcano":null,"tungen Grass":null,"tungen Vulcano":null},"SpeckyCut":{"Garden":6.0,"Grass":null,"T\u00f6tung Grass":null,"T\u00f6tungen Grass":4.0,"T\u00f6tungen Vulcano":5.0,"Vulcano":null,"tungen Grass":null,"tungen Vulcano":null},"StaudammAusHolz":{"Garden":6.0,"Grass":null,"T\u00f6tung Grass":null,"T\u00f6tungen Grass":7.0,"T\u00f6tungen Vulcano":6.0,"Vulcano":null,"tungen Grass":null,"tungen Vulcano":null},"Tomiokey":{"Garden":9.0,"Grass":null,"T\u00f6tung Grass":null,"T\u00f6tungen Grass":7.0,"T\u00f6tungen Vulcano":8.0,"Vulcano":null,"tungen Grass":null,"tungen Vulcano":null},"tsuneee":{"Garden":6.0,"Grass":null,"T\u00f6tung Grass":null,"T\u00f6tungen Grass":6.0,"T\u00f6tungen Vulcano":7.0,"Vulcano":null,"tungen Grass":null,"tungen Vulcano":null},"twitchparaskiill":{"Garden":7.0,"Grass":null,"T\u00f6tung Grass":null,"T\u00f6tungen Grass":7.0,"T\u00f6tungen Vulcano":6.0,"Vulcano":null,"tungen Grass":null,"tungen Vulcano":null},"Txlentierter":{"Garden":null,"Grass":1.0,"T\u00f6tung Grass":null,"T\u00f6tungen Grass":null,"T\u00f6tungen Vulcano":null,"Vulcano":null,"tungen Grass":null,"tungen Vulcano":null},"Umgfoin":{"Garden":6.0,"Grass":null,"T\u00f6tung Grass":null,"T\u00f6tungen Grass":6.0,"T\u00f6tungen Vulcano":9.0,"Vulcano":null,"tungen Grass":null,"tungen Vulcano":null},"WirdNichtGeladen":{"Garden":5.0,"Grass":null,"T\u00f6tung Grass":null,"T\u00f6tungen Grass":7.0,"T\u00f6tungen Vulcano":8.0,"Vulcano":null,"tungen Grass":null,"tungen Vulcano":null},"Wissender":{"Garden":8.0,"Grass":null,"T\u00f6tung Grass":null,"T\u00f6tungen Grass":6.0,"T\u00f6tungen Vulcano":6.0,"Vulcano":null,"tungen Grass":null,"tungen Vulcano":null},"xBaumeisterin":{"Garden":5.0,"Grass":null,"T\u00f6tung Grass":null,"T\u00f6tungen Grass":5.0,"T\u00f6tungen Vulcano":6.0,"Vulcano":null,"tungen Grass":null,"tungen Vulcano":null},"xX_Dima_ggg_Xx6":{"Garden":9.0,"Grass":null,"T\u00f6tung Grass":null,"T\u00f6tungen Grass":8.0,"T\u00f6tungen Vulcano":10.0,"Vulcano":null,"tungen Grass":null,"tungen Vulcano":null},"xX_Masha_ggg_Xx9":{"Garden":5.0,"Grass":null,"T\u00f6tung Grass":null,"T\u00f6tungen Grass":5.0,"T\u00f6tungen Vulcano":6.0,"Vulcano":null,"tungen Grass":null,"tungen Vulcano":null},"ymq_":{"Garden":9.0,"Grass":null,"T\u00f6tung Grass":null,"T\u00f6tungen Grass":11.0,"T\u00f6tungen Vulcano":10.0,"Vulcano":null,"tungen Grass":null,"tungen Vulcano":null},"yzvm":{"Garden":9.0,"Grass":null,"T\u00f6tung Grass":null,"T\u00f6tungen Grass":10.0,"T\u00f6tungen Vulcano":11.0,"Vulcano":null,"tungen Grass":null,"tungen Vulcano":null},"zTotito":{"Garden":10.0,"Grass":null,"T\u00f6tung Grass":null,"T\u00f6tungen Grass":11.0,"T\u00f6tungen Vulcano":9.0,"Vulcano":null,"tungen Grass":null,"tungen Vulcano":null},"_n3d":{"Garden":10.0,"Grass":null,"T\u00f6tung Grass":null,"T\u00f6tungen Grass":8.0,"T\u00f6tungen Vulcano":9.0,"Vulcano":null,"tungen Grass":null,"tungen Vulcano":null},"_Waldi_":{"Garden":5.0,"Grass":null,"T\u00f6tung Grass":null,"T\u00f6tungen Grass":8.0,"T\u00f6tungen Vulcano":6.0,"Vulcano":null,"tungen Grass":null,"tungen Vulcano":null}}